<annotation><filename>274p.jpg</filename><folder>users/robert4213//pothole_data/training_data</folder><source><submittedBy>Shiyan Cai</submittedBy></source><imagesize><nrows>225</nrows><ncols>300</ncols></imagesize><object><name>pothole</name><deleted>0</deleted><verified>0</verified><occluded>no</occluded><attributes>3</attributes><parts><hasparts></hasparts><ispartof></ispartof></parts><date>18-Mar-2019 07:26:56</date><id>0</id><polygon><username>Shiyan Cai</username><pt><x>299</x><y>170</y></pt><pt><x>180</x><y>112</y></pt><pt><x>25</x><y>118</y></pt><pt><x>21</x><y>210</y></pt></polygon></object></annotation>