<annotation><filename>334p.jpg</filename><folder>users/robert4213//pothole_data/training_data</folder><source><submittedBy>Shiyan Cai</submittedBy></source><imagesize><nrows>900</nrows><ncols>900</ncols></imagesize><object><name>pothole</name><deleted>0</deleted><verified>0</verified><occluded>no</occluded><attributes>1</attributes><parts><hasparts></hasparts><ispartof></ispartof></parts><date>18-Mar-2019 07:42:34</date><id>0</id><polygon><username>Shiyan Cai</username><pt><x>190</x><y>421</y></pt><pt><x>271</x><y>497</y></pt><pt><x>726</x><y>331</y></pt><pt><x>594</x><y>295</y></pt></polygon></object></annotation>