<annotation><filename>77n.jpg</filename><folder>users/robert4213//pothole_data/training_data</folder><source><submittedBy>Shiyan Cai</submittedBy></source><imagesize><nrows>624</nrows><ncols>1000</ncols></imagesize><object><name>shadow</name><deleted>0</deleted><verified>0</verified><occluded>no</occluded><attributes></attributes><parts><hasparts></hasparts><ispartof></ispartof></parts><date>21-Mar-2019 05:46:03</date><id>0</id><type>bounding_box</type><polygon><username>anonymous</username><pt><x>251</x><y>439</y></pt><pt><x>346</x><y>439</y></pt><pt><x>346</x><y>429</y></pt><pt><x>251</x><y>429</y></pt></polygon></object></annotation>