<annotation><filename>extra261.jpg</filename><folder>users/myu121//newdata2</folder><source><submittedBy>MICHAEL YU</submittedBy></source><imagesize><nrows>168</nrows><ncols>299</ncols></imagesize><object><name>pothole3</name><deleted>0</deleted><verified>0</verified><occluded>no</occluded><attributes></attributes><parts><hasparts></hasparts><ispartof></ispartof></parts><date>09-May-2019 22:52:00</date><id>0</id><polygon><username>mike</username><pt><x>119</x><y>64</y></pt><pt><x>37</x><y>165</y></pt><pt><x>234</x><y>167</y></pt><pt><x>272</x><y>70</y></pt><pt><x>117</x><y>63</y></pt></polygon></object></annotation>