<annotation><filename>pothole_pos521.jpg</filename><folder>users/robert4213//pothole_data/extra_data</folder><source><submittedBy>Shiyan Cai</submittedBy></source><imagesize><nrows>562</nrows><ncols>1000</ncols></imagesize><object><name>pothole3</name><deleted>0</deleted><verified>0</verified><occluded>no</occluded><attributes></attributes><parts><hasparts></hasparts><ispartof></ispartof></parts><date>02-May-2019 05:21:32</date><id>0</id><type>bounding_box</type><polygon><username>anonymous</username><pt><x>28</x><y>219</y></pt><pt><x>930</x><y>219</y></pt><pt><x>930</x><y>354</y></pt><pt><x>28</x><y>354</y></pt></polygon></object><object><name>pothole0</name><deleted>0</deleted><verified>0</verified><occluded>no</occluded><attributes></attributes><parts><hasparts></hasparts><ispartof></ispartof></parts><date>02-May-2019 05:21:40</date><id>1</id><type>bounding_box</type><polygon><username>anonymous</username><pt><x>59</x><y>7</y></pt><pt><x>880</x><y>7</y></pt><pt><x>880</x><y>181</y></pt><pt><x>59</x><y>181</y></pt></polygon></object><object><name>pothole0</name><deleted>0</deleted><verified>0</verified><occluded>no</occluded><attributes></attributes><parts><hasparts></hasparts><ispartof></ispartof></parts><date>02-May-2019 05:21:44</date><id>2</id><type>bounding_box</type><polygon><username>anonymous</username><pt><x>28</x><y>373</y></pt><pt><x>976</x><y>373</y></pt><pt><x>976</x><y>560</y></pt><pt><x>28</x><y>560</y></pt></polygon></object></annotation>