<annotation><filename>pothole_pos357.jpg</filename><folder>users/myu121//newdata</folder><source><submittedBy>MICHAEL YU</submittedBy></source><imagesize><nrows>863</nrows><ncols>1300</ncols></imagesize><object><name>pothole2</name><deleted>0</deleted><verified>0</verified><occluded>no</occluded><attributes></attributes><parts><hasparts></hasparts><ispartof></ispartof></parts><date>02-May-2019 20:16:40</date><id>0</id><polygon><username>anonymous</username><pt><x>627</x><y>322</y></pt><pt><x>768</x><y>329</y></pt><pt><x>847</x><y>417</y></pt><pt><x>925</x><y>520</y></pt><pt><x>919</x><y>615</y></pt><pt><x>739</x><y>676</y></pt><pt><x>478</x><y>647</y></pt><pt><x>338</x><y>531</y></pt><pt><x>383</x><y>399</y></pt><pt><x>468</x><y>324</y></pt></polygon></object></annotation>