<annotation><filename>pothole_pos71.jpg</filename><folder>users/kles90105//extra_data</folder><source><submittedBy>Chen-Feng Huang</submittedBy></source><imagesize><nrows>366</nrows><ncols>650</ncols></imagesize><object><name>pothole3</name><deleted>0</deleted><verified>0</verified><occluded>no</occluded><attributes></attributes><parts><hasparts></hasparts><ispartof></ispartof></parts><date>02-May-2019 21:03:56</date><id>0</id><type>bounding_box</type><polygon><username>Bert</username><pt><x>172</x><y>133</y></pt><pt><x>641</x><y>133</y></pt><pt><x>641</x><y>273</y></pt><pt><x>172</x><y>273</y></pt></polygon></object><object><name>pothole3</name><deleted>0</deleted><verified>0</verified><occluded>no</occluded><attributes></attributes><parts><hasparts></hasparts><ispartof></ispartof></parts><date>02-May-2019 21:04:02</date><id>1</id><type>bounding_box</type><polygon><username>Bert</username><pt><x>242</x><y>105</y></pt><pt><x>5</x><y>105</y></pt><pt><x>5</x><y>55</y></pt><pt><x>242</x><y>55</y></pt></polygon></object><object><name>pothole3</name><deleted>0</deleted><verified>0</verified><occluded>no</occluded><attributes></attributes><parts><hasparts></hasparts><ispartof></ispartof></parts><date>02-May-2019 21:04:09</date><id>2</id><type>bounding_box</type><polygon><username>Bert</username><pt><x>307</x><y>95</y></pt><pt><x>478</x><y>95</y></pt><pt><x>478</x><y>144</y></pt><pt><x>307</x><y>144</y></pt></polygon></object></annotation>