<annotation><filename>pothole_neg219.jpg</filename><folder>users/pwy0424//pothole_extra/negative</folder><source><submittedBy>Weiyang Pan</submittedBy></source><imagesize><nrows>1944</nrows><ncols>2592</ncols></imagesize><object><name>sewer cover0</name><deleted>0</deleted><verified>0</verified><occluded>no</occluded><attributes>0</attributes><parts><hasparts></hasparts><ispartof></ispartof></parts><date>03-May-2019 09:22:23</date><id>0</id><type>bounding_box</type><polygon><username>pwy0424</username><pt><x>301</x><y>539</y></pt><pt><x>1616</x><y>539</y></pt><pt><x>1616</x><y>1257</y></pt><pt><x>301</x><y>1257</y></pt></polygon></object><object><name>noise</name><deleted>0</deleted><verified>0</verified><occluded>no</occluded><attributes>0</attributes><parts><hasparts></hasparts><ispartof></ispartof></parts><date>03-May-2019 09:22:42</date><id>1</id><type>bounding_box</type><polygon><username>pwy0424</username><pt><x>878</x><y>137</y></pt><pt><x>1901</x><y>137</y></pt><pt><x>1901</x><y>1027</y></pt><pt><x>878</x><y>1027</y></pt></polygon></object></annotation>