<annotation><filename>pothole_pos48.jpg</filename><folder>users/kles90105//extra_data</folder><source><submittedBy>Chen-Feng Huang</submittedBy></source><imagesize><nrows>720</nrows><ncols>1280</ncols></imagesize><object><name>pothole2</name><deleted>0</deleted><verified>0</verified><occluded>no</occluded><attributes></attributes><parts><hasparts></hasparts><ispartof></ispartof></parts><date>02-May-2019 20:59:53</date><id>0</id><type>bounding_box</type><polygon><username>Bert</username><pt><x>562</x><y>601</y></pt><pt><x>350</x><y>601</y></pt><pt><x>350</x><y>515</y></pt><pt><x>562</x><y>515</y></pt></polygon></object><object><name>pothole3</name><deleted>0</deleted><verified>0</verified><occluded>no</occluded><attributes></attributes><parts><hasparts></hasparts><ispartof></ispartof></parts><date>02-May-2019 20:59:57</date><id>1</id><type>bounding_box</type><polygon><username>Bert</username><pt><x>690</x><y>530</y></pt><pt><x>468</x><y>530</y></pt><pt><x>468</x><y>406</y></pt><pt><x>690</x><y>406</y></pt></polygon></object><object><name>pothole2</name><deleted>0</deleted><verified>0</verified><occluded>no</occluded><attributes></attributes><parts><hasparts></hasparts><ispartof></ispartof></parts><date>02-May-2019 21:00:00</date><id>2</id><type>bounding_box</type><polygon><username>Bert</username><pt><x>302</x><y>544</y></pt><pt><x>123</x><y>544</y></pt><pt><x>123</x><y>437</y></pt><pt><x>302</x><y>437</y></pt></polygon></object><object><name>pothole3</name><deleted>0</deleted><verified>0</verified><occluded>no</occluded><attributes></attributes><parts><hasparts></hasparts><ispartof></ispartof></parts><date>02-May-2019 21:00:12</date><id>3</id><type>bounding_box</type><polygon><username>Bert</username><pt><x>463</x><y>356</y></pt><pt><x>26</x><y>356</y></pt><pt><x>26</x><y>221</y></pt><pt><x>463</x><y>221</y></pt></polygon></object></annotation>