<annotation><filename>pwy0068.jpg</filename><folder>users/pwy0424//pothole/positive</folder><source><submittedBy>Weiyang Pan</submittedBy></source><imagesize><nrows>409</nrows><ncols>615</ncols></imagesize><object><name>pothole</name><deleted>0</deleted><verified>0</verified><occluded>no</occluded><attributes></attributes><parts><hasparts></hasparts><ispartof></ispartof></parts><date>24-Mar-2019 02:55:18</date><id>0</id><type>bounding_box</type><polygon><username>pwy0424</username><pt><x>67</x><y>271</y></pt><pt><x>286</x><y>271</y></pt><pt><x>286</x><y>386</y></pt><pt><x>67</x><y>386</y></pt></polygon></object><object><name>crack</name><deleted>0</deleted><verified>0</verified><occluded>no</occluded><attributes></attributes><parts><hasparts></hasparts><ispartof></ispartof></parts><date>24-Mar-2019 02:55:21</date><id>1</id><type>bounding_box</type><polygon><username>pwy0424</username><pt><x>421</x><y>195</y></pt><pt><x>573</x><y>195</y></pt><pt><x>573</x><y>329</y></pt><pt><x>421</x><y>329</y></pt></polygon></object></annotation>